dharitri_sdk/__init__.py
dharitri_sdk/abi/__init__.py
dharitri_sdk/abi/abi.py
dharitri_sdk/abi/abi_definition.py
dharitri_sdk/abi/abi_test.py
dharitri_sdk/abi/address_value.py
dharitri_sdk/abi/address_value_test.py
dharitri_sdk/abi/array_value.py
dharitri_sdk/abi/array_value_test.py
dharitri_sdk/abi/bigint_value.py
dharitri_sdk/abi/biguint_value.py
dharitri_sdk/abi/bool_value.py
dharitri_sdk/abi/bytes_value.py
dharitri_sdk/abi/bytes_value_test.py
dharitri_sdk/abi/codec.py
dharitri_sdk/abi/constants.py
dharitri_sdk/abi/counted_variadic_values.py
dharitri_sdk/abi/counted_variadic_values_test.py
dharitri_sdk/abi/enum_value.py
dharitri_sdk/abi/enum_value_test.py
dharitri_sdk/abi/fields.py
dharitri_sdk/abi/fields_test.py
dharitri_sdk/abi/interface.py
dharitri_sdk/abi/list_value.py
dharitri_sdk/abi/list_value_test.py
dharitri_sdk/abi/multi_value.py
dharitri_sdk/abi/multi_value_test.py
dharitri_sdk/abi/option_value.py
dharitri_sdk/abi/option_value_test.py
dharitri_sdk/abi/optional_value.py
dharitri_sdk/abi/optional_value_test.py
dharitri_sdk/abi/parts.py
dharitri_sdk/abi/serializer.py
dharitri_sdk/abi/serializer_test.py
dharitri_sdk/abi/shared.py
dharitri_sdk/abi/shared_test.py
dharitri_sdk/abi/small_int_values.py
dharitri_sdk/abi/string_value.py
dharitri_sdk/abi/string_value_test.py
dharitri_sdk/abi/struct_value.py
dharitri_sdk/abi/struct_value_test.py
dharitri_sdk/abi/token_identifier_value.py
dharitri_sdk/abi/tuple_value.py
dharitri_sdk/abi/tuple_value_test.py
dharitri_sdk/abi/type_formula.py
dharitri_sdk/abi/type_formula_parser.py
dharitri_sdk/abi/type_formula_parser_test.py
dharitri_sdk/abi/typesystem.py
dharitri_sdk/abi/typesystem_test.py
dharitri_sdk/abi/variadic_values.py
dharitri_sdk/abi/variadic_values_test.py
dharitri_sdk/adapters/__init__.py
dharitri_sdk/adapters/query_runner_adapter.py
dharitri_sdk/converters/__init__.py
dharitri_sdk/converters/errors.py
dharitri_sdk/converters/transactions_converter.py
dharitri_sdk/converters/transactions_converter_test.py
dharitri_sdk-0.11.1.dist-info/METADATA
dharitri_sdk-0.11.1.dist-info/WHEEL
dharitri_sdk-0.11.1.dist-info/licenses/LICENSE
dharitri_sdk-0.11.1.dist-info/RECORD
