Metadata-Version: 2.3
Name: dharitri-sdk
Version: 0.11.1
Summary: The Dharitri Python SDK.
Project-URL: Homepage, https://github.com/DharitriOne/drt-sdk-py
Author: Dharitri
License-Expression: MIT
License-File: LICENSE
Classifier: License :: OSI Approved :: MIT License
Classifier: Operating System :: OS Independent
Classifier: Programming Language :: Python :: 3
Requires-Python: >=3.8
Requires-Dist: cryptography==42.0.4
Requires-Dist: mnemonic==0.20
Requires-Dist: protobuf==5.27.2
Requires-Dist: pycryptodomex==3.19.1
Requires-Dist: pynacl==1.5.0
Requires-Dist: requests==2.32.0
